[
  {
    "id": 1,
    "title": "Number and Counting Learning Board",
    "bangla": "সংখ্যা ও গণনা শেখার শিক্ষামূলক বোর্ড",
    "image": "https://i.ibb.co.com/p6Q0fchX/81a72-DDFc-KL-AC-SL1500.jpg",
    "price": 1250,
    "discount": 10,
    "sizes": [],
    "color": [],
    "description": "Number and Counting Learning Board টি শিশুদের প্রাথমিক গণিত শেখার জন্য একটি কার্যকর educational toy।\n\nএই learning board এর মাধ্যমে বাচ্চারা ১ থেকে ২০ পর্যন্ত সংখ্যা চিনতে শেখে...",
    "qna": [
      {
        "question": "এই বোর্ডটি কোন বয়সের শিশুদের জন্য উপযুক্ত?",
        "answer": "৩ থেকে ৬ বছর বয়সী শিশুদের জন্য এটি সবচেয়ে উপযোগী।"
      }
    ],
    "reviews": 19,
    "sold": 31,
    "ratings": 4.6,
    "info": [
      "সংখ্যা ও গণনার ধারণা তৈরি করে",
      "প্রাথমিক গণিত শেখার জন্য উপযোগী"
    ]
  },

  {
    "id": 2,
    "title": "Animal and Nature Learning Flash Cards",
    "bangla": "প্রাণী ও প্রকৃতি শেখার ফ্ল্যাশ কার্ড সেট",
    "image": "https://i.ibb.co.com/QFDWpCf4/s-l1600.webp",
    "price": 950,
    "discount": 8,
    "sizes": [],
    "color": [],
    "description": "Animal and Nature Learning Flash Cards সেটটি শিশুদের চারপাশের জগৎ সম্পর্কে শেখার আগ্রহ তৈরি করার জন্য ডিজাইন করা হয়েছে...",
    "qna": [],
    "reviews": 22,
    "sold": 40,
    "ratings": 4.7,
    "info": []
  },

  {
    "id": 3,
    "title": "Fun Logic Matching Cube Game",
    "bangla": "মজার লজিক ম্যাচিং কিউব গেম",
    "image": "https://i.ibb.co.com/3mMvjKnV/71k8-US2-Ls3-L-SL1500.jpg",
    "price": 1150,
    "discount": 14,
    "sizes": [],
    "color": [],
    "description": "Fun Logic Matching Cube Game একটি playful কিন্তু highly educational toy...",
    "qna": [],
    "reviews": 26,
    "sold": 48,
    "ratings": 4.6,
    "info": []
  },

  {
    "id": 4,
    "title": "Creative Story Builder Picture Cards",
    "bangla": "মজার গল্প বানানোর পিকচার কার্ড সেট",
    "image": "https://i.ibb.co.com/RGMWJdwt/71zppz-Gon-RL-AC-SX679.jpg",
    "price": 1050,
    "discount": 9,
    "sizes": [],
    "color": [],
    "description": "Creative Story Builder Picture Cards একটি fun-filled learning toy...",
    "qna": [],
    "reviews": 21,
    "sold": 37,
    "ratings": 4.7,
    "info": []
  },

  {
    "id": 5,
    "title": "Kids Graduation Hat with Costume",
    "bangla": "শিশুদের গ্র্যাজুয়েশন হ্যাট ( কস্টিউম সহ )",
    "image": "https://i.ibb.co.com/vxMYHV6V/image.png",
    "price": 650,
    "discount": 5,
    "sizes": [],
    "color": [],
    "description": "Kids Graduation Hat শিশুদের জন্য একটি মজার এবং স্মরণীয় educational accessory...",
    "qna": [],
    "reviews": 15,
    "sold": 28,
    "ratings": 4.4,
    "info": []
  },

  {
    "id": 6,
    "title": "Superman Costume for Kids",
    "bangla": "শিশুদের সুপারম্যান পোশাক",
    "image": "https://i.ibb.co.com/1tNhx5Ct/81-Vy-ni-Yxs-L-AC-SX679.jpg",
    "price": 1350,
    "discount": 10,
    "sizes": [],
    "color": [],
    "description": "Superman Costume শিশুদের imaginative play এর জন্য perfect...",
    "qna": [],
    "reviews": 18,
    "sold": 32,
    "ratings": 4.6,
    "info": []
  },

  {
    "id": 7,
    "title": "Doctor Costume Set for Kids",
    "bangla": "শিশুদের ডাক্তার পোশাক সেট",
    "image": "https://i.ibb.co.com/203h05Sq/image.png",
    "price": 1450,
    "discount": 12,
    "sizes": [],
    "color": [],
    "description": "Doctor Costume Set শিশুদের role-playing এর জন্য perfect...",
    "qna": [],
    "reviews": 20,
    "sold": 30,
    "ratings": 4.7,
    "info": []
  },

  {
    "id": 8,
    "title": "Kids Engineering Tools Set",
    "bangla": "শিশুদের ইঞ্জিনিয়ারিং টুলস সেট",
    "image": "https://i.ibb.co.com/W4L8SFbK/image.png",
    "price": 1350,
    "discount": 10,
    "sizes": [],
    "color": [],
    "description": "Kids Engineering Tools Set শিশুদের hands-on learning এর জন্য তৈরি...",
    "qna": [],
    "reviews": 18,
    "sold": 28,
    "ratings": 4.6,
    "info": []
  }
]